Workbook

Sheet Inventory
A1: Brand Name | B1: Model Name | C1: Product ID | D1: Desription | E1: Cost Price | F1: Selling Price | G1: Quantity Bought | H1: Quantity Sold | I1: Promo Quantity | J1: Stock Left
A2: Samsung | B2: SAM-Q60A | C2: TV-Sam-001 | D2: OLED 50-inch 4K Ultra HD Smart TV with HDR | E2: 3750 | F2: =E2 * 1.3 -> 4875 | G2: 15 | H2: =Sales!D2 -> 2 | I2: 0 | J2: =G2-H2-I2 -> 13
A3: Samsung | B3: SAM-Q70A | C3: ="TV-"&LEFT(A3,3)&"-"&TEXT(ROW()-1,"000") -> TV-Sam-002 | D3: OLED 55-inch 4K Smart TV with Dolby Vision | E3: 4750 | F3: =E3 * 1.3 -> 6175 | G3: 15 | H3: =Sales!D3 -> 4 | I3: 0 | J3: =G3-H3-I3 -> 11
A4: Samsung | B4: SAM-Q80A | C4: ="TV-"&LEFT(A4,3)&"-"&TEXT(ROW()-1,"000") -> TV-Sam-003 | D4: OLED 65-inch Ultra HD TV with cinematic colors | E4: 5750 | F4: =E4 * 1.3 -> 7475 | G4: 15 | H4: =Sales!D4 -> 2 | I4: 0 | J4: =G4-H4-I4 -> 13
A5: Samsung | B5: SAM-Q90A | C5: ="TV-"&LEFT(A5,3)&"-"&TEXT(ROW()-1,"000") -> TV-Sam-004 | D5: OLED 48-inch Smart TV with ultra-thin design | E5: 7250 | F5: =E5 * 1.3 -> 9425 | G5: 15 | H5: =Sales!D5 -> 0 | I5: 0 | J5: =G5-H5-I5 -> 15
A6: Samsung | B6: SAM-AU7000 | C6: ="TV-"&LEFT(A6,3)&"-"&TEXT(ROW()-1,"000") -> TV-Sam-005 | D6: OLED 77-inch premium 4K Smart TV | E6: 2250 | F6: =E6 * 1.3 -> 2925 | G6: 15 | H6: =Sales!D6 -> 0 | I6: 0 | J6: =G6-H6-I6 -> 15
A7: Samsung | B7: SAM-AU8000 | C7: ="TV-"&LEFT(A7,3)&"-"&TEXT(ROW()-1,"000") -> TV-Sam-006 | D7: QLED 50-inch 4K Smart TV with vibrant display | E7: 2750 | F7: =E7 * 1.3 -> 3575 | G7: 15 | H7: =Sales!D7 -> 2 | I7: 0 | J7: =G7-H7-I7 -> 13
A8: Samsung | B8: SAM-TU7000 | C8: ="TV-"&LEFT(A8,3)&"-"&TEXT(ROW()-1,"000") -> TV-Sam-007 | D8: QLED 55-inch HDR Smart TV with wide color gamut | E8: 2250 | F8: =E8 * 1.3 -> 2925 | G8: 15 | H8: =Sales!D8 -> 0 | I8: 0 | J8: =G8-H8-I8 -> 15
A9: Samsung | B9: SAM-TU8000 | C9: ="TV-"&LEFT(A9,3)&"-"&TEXT(ROW()-1,"000") -> TV-Sam-008 | D9: QLED 65-inch Ultra HD TV with quantum color | E9: 2750 | F9: =E9 * 1.3 -> 3575 | G9: 15 | H9: =Sales!D9 -> 3 | I9: 0 | J9: =G9-H9-I9 -> 12
A10: Samsung | B10: SAM-S95B | C10: ="TV-"&LEFT(A10,3)&"-"&TEXT(ROW()-1,"000") -> TV-Sam-009 | D10: QLED 65-inch Ultra HD TV with quantum color | E10: 8000 | F10: =E10 * 1.3 -> 10400 | G10: 15 | H10: =Sales!D10 -> 9 | I10: 0 | J10: =G10-H10-I10 -> 6
A11: Samsung | B11: SAM-Q60A | C11: ="TV-"&LEFT(A11,3)&"-"&TEXT(ROW()-1,"000") -> TV-Sam-010 | D11: QLED 43-inch 4K Smart TV for home use | E11: 8500 | F11: =E11 * 1.3 -> 11050 | G11: 15 | H11: =Sales!D11 -> 1 | I11: 0 | J11: =G11-H11-I11 -> 14
A12: LG | B12: LG-UQ7500 | C12: TV-LG-001 | D12: LED 32-inch HD Ready TV with slim bezels | E12: 2000 | F12: =E12 * 1.3 -> 2600 | G12: 15 | H12: =Sales!D12 -> 0 | I12: 0 | J12: =G12-H12-I12 -> 15
A13: LG | B13: LG-UQ8000 | C13: TV-LG-002 | D13: LED 40-inch Full HD TV with clear motion | E13: 2500 | F13: =E13 * 1.3 -> 3250 | G13: 15 | H13: =Sales!D13 -> 0 | I13: 0 | J13: =G13-H13-I13 -> 15
A14: LG | B14: LG-NANO75 | C14: TV-LG-003 | D14: LED 43-inch Smart TV with built-in apps | E14: 3000 | F14: =E14 * 1.3 -> 3900 | G14: 15 | H14: =Sales!D14 -> 0 | I14: 0 | J14: =G14-H14-I14 -> 15
A15: LG | B15: LG-NANO85 | C15: TV-LG-004 | D15: LED 50-inch 4K Ultra HD Smart TV | E15: 4000 | F15: =E15 * 1.3 -> 5200 | G15: 15 | H15: =Sales!D15 -> 0 | I15: 0 | J15: =G15-H15-I15 -> 15
A16: LG | B16: LG-NANO90 | C16: TV-LG-005 | D16: LED 55-inch Smart TV with HDR support | E16: 4500 | F16: =E16 * 1.3 -> 5850 | G16: 15 | H16: =Sales!D16 -> 0 | I16: 0 | J16: =G16-H16-I16 -> 15
A17: LG | B17: LG-C1 | C17: TV-LG-006 | D17: LED 65-inch 4K TV with enhanced contrast | E17: 6000 | F17: =E17 * 1.3 -> 7800 | G17: 15 | H17: =Sales!D17 -> 0 | I17: 0 | J17: =G17-H17-I17 -> 15
A18: LG | B18: LG-C2 | C18: TV-LG-007 | D18: LED 75-inch Ultra HD TV for home cinema | E18: 7000 | F18: =E18 * 1.3 -> 9100 | G18: 15 | H18: =Sales!D18 -> 0 | I18: 0 | J18: =G18-H18-I18 -> 15
A19: LG | B19: LG-G1 | C19: TV-LG-008 | D19: LED 24-inch HD TV for small rooms | E19: 8500 | F19: =E19 * 1.3 -> 11050 | G19: 15 | H19: =Sales!D19 -> 0 | I19: 0 | J19: =G19-H19-I19 -> 15
A20: LG | B20: LG-B2 | C20: TV-LG-009 | D20: LED 28-inch compact HD television | E20: 6500 | F20: =E20 * 1.3 -> 8450 | G20: 15 | H20: =Sales!D20 -> 0 | I20: 0 | J20: =G20-H20-I20 -> 15
A21: LG | B21: LG-QNED80 | C21: TV-LG-010 | D21: LED 60-inch Smart TV with immersive display | E21: 7500 | F21: =E21 * 1.3 -> 9750 | G21: 15 | H21: =Sales!D21 -> 0 | I21: 0 | J21: =G21-H21-I21 -> 15
A22: Sony | B22: SONY-X75K | C22: TV-Son-001 | D22: Mini-LED 55-inch 4K Smart TV with deep blacks | E22: 3000 | F22: =E22 * 1.3 -> 3900 | G22: 15 | H22: =Sales!D22 -> 0 | I22: 0 | J22: =G22-H22-I22 -> 15
A23: Sony | B23: SONY-X80K | C23: TV-Son-002 | D23: Mini-LED 65-inch Ultra HD TV with high brightness | E23: 3500 | F23: =E23 * 1.3 -> 4550 | G23: 15 | H23: =Sales!D23 -> 1 | I23: 0 | J23: =G23-H23-I23 -> 14
... A101: Toshiba | B101: TOS-Z670 | C101: TV-Tos-010 | D101: Luxury 50-inch OLED Smart TV | E101: 3500 | F101: =E101 * 1.3 -> 4550 | G101: 15 | H101: =Sales!D101 -> 1 | I101: 0 | J101: =G101-H101-I101 -> 14

Sheet Sales
A1: Brand | B1: Model | C1: Selling Price | D1: Quantity Sold | E1: Total Revenue
A2: Samsung | B2: SAM-Q60A | C2: =Inventory!E2*1.3 -> 4875 | D2: 2 | E2: =C2 * D2 -> 9750
A3: Samsung | B3: SAM-Q70A | C3: =Inventory!E3*1.3 -> 6175 | D3: 4 | E3: =C3 * D3 -> 24700
A4: Samsung | B4: SAM-Q80A | C4: =Inventory!E4*1.3 -> 7475 | D4: 2 | E4: =C4 * D4 -> 14950
A5: Samsung | B5: SAM-Q90A | C5: =Inventory!E5*1.3 -> 9425 | D5: 0 | E5: =C5 * D5 -> 0
A6: Samsung | B6: SAM-AU7000 | C6: =Inventory!E6*1.3 -> 2925 | D6: 0 | E6: =C6 * D6 -> 0
A7: Samsung | B7: SAM-AU8000 | C7: =Inventory!E7*1.3 -> 3575 | D7: 2 | E7: =C7 * D7 -> 7150
A8: Samsung | B8: SAM-TU7000 | C8: =Inventory!E8*1.3 -> 2925 | D8: 0 | E8: =C8 * D8 -> 0
A9: Samsung | B9: SAM-TU8000 | C9: =Inventory!E9*1.3 -> 3575 | D9: 3 | E9: =C9 * D9 -> 10725
A10: Samsung | B10: SAM-S95B | C10: =Inventory!E10*1.3 -> 10400 | D10: 9 | E10: =C10 * D10 -> 93600
A11: Samsung | B11: SAM-Q60A | C11: =Inventory!E11*1.3 -> 11050 | D11: 1 | E11: =C11 * D11 -> 11050
A12: LG | B12: LG-UQ7500 | C12: =Inventory!E12*1.3 -> 2600 | D12: 0 | E12: =C12 * D12 -> 0
A13: LG | B13: LG-UQ8000 | C13: =Inventory!E13*1.3 -> 3250 | D13: 0 | E13: =C13 * D13 -> 0
... A101: Toshiba | B101: TOS-Z670 | C101: =Inventory!E101*1.3 -> 4550 | D101: 1 | E101: =C101 * D101 -> 4550

Sheet Salary
A1: Employee's ID | B1: Name | C1: Brand Name | D1: fix monthly salary | E1: Total Sales Revenue | F1: Commission | G1: Total salary for Jan
A2: EMP-001 | B2: Adam | C2: Samsung & LG | D2: 8000 | E2: =SUM(Sales!E2:E11,Sales!E12:E21) -> 171925 | F2: =IF(E2>15000,E2*0.5,E2*0.05) -> 85962.5 | G2: =(D2+F2) -> 93962.5
A3: EMP-002 | B3: Brian | C3: Sony & TCL | D3: 8000 | E3: =SUM(Sales!E22:E41) -> 140400 | F3: =IF(E3>15000,E3*0.5,E3*0.05) -> 70200 | G3: =(D3+F3) -> 78200
A4: EMP-003 | B4: Chloe | C4: Hisense & Sharp | D4: 8000 | E4: =SUM(Sales!E42:E61) -> 17810 | F4: =IF(E4>15000,E4*0.5,E4*0.05) -> 8905 | G4: =(D4+F4) -> 16905
A5: EMP-004 | B5: Daniel | C5: Panasonic & Philips | D5: 8000 | E5: =SUM(Sales!E62:E81) -> 32890 | F5: =IF(E5>15000,E5*0.5,E5*0.05) -> 16445 | G5: =(D5+F5) -> 24445
A6: EMP-005 | B6: Ethan | C6: Xiaomi & Toshiba | D6: 8000 | E6: =SUM(Sales!E82:E101) -> 53170 | F6: =IF(E6>15000,E6*0.5,E6*0.05) -> 26585 | G6: =(D6+F6) -> 34585

Sheet Analysis
A1: Brand | B1: Total Bought | C1: Total Sold | D1: Promo Quantity | E1: Stock Left | G1: Metric | H1: Value | J1: SUM Total Sales Revenue | K1: SUM Commission | L1: SUM Final Salary | M1: Column1 | N1: Employee | O1: Total Sales Revenue | P1: Commission | Q1: Final Salary
A2: Panasonic | B2: =SUMIF(Inventory!A:A,A2,Inventory!G:G) -> 150 | C2: =SUMIF(Inventory!A:A,A2,Inventory!H:H) -> 3 | D2: =SUMIF(Inventory!A:A,A2,Inventory!I:I) -> 0 | E2: =SUMIF(Inventory!A:A,A2,Inventory!J:J) -> 147 | G2: Total Revenue | H2: =SUM(Sales!E:E) -> 416195 | J2: =SUM(Salary!E:E) -> 416195 | K2: =SUM(Salary!F:F) -> 208097.5 | L2: =SUM(Salary!G:G) -> 248097.5 | N2: Adam | O2: =INDEX(Salary!E:E,2) -> 171925 | P2: =INDEX(Salary!F:F,2) -> 85962.5 | Q2: =INDEX(Salary!G:G,2) -> 93962.5
A3: TCL | B3: =SUMIF(Inventory!A:A,A3,Inventory!G:G) -> 150 | C3: =SUMIF(Inventory!A:A,A3,Inventory!H:H) -> 0 | D3: =SUMIF(Inventory!A:A,A3,Inventory!I:I) -> 0 | E3: =SUMIF(Inventory!A:A,A3,Inventory!J:J) -> 150 | G3: Total Quantity Sold | H3: =SUM(Sales!D:D) -> 76 | N3: Brian | O3: =INDEX(Salary!E:E,3) -> 140400 | P3: =INDEX(Salary!F:F,3) -> 70200 | Q3: =INDEX(Salary!G:G,3) -> 78200
A4: Hisense | B4: =SUMIF(Inventory!A:A,A4,Inventory!G:G) -> 150 | C4: =SUMIF(Inventory!A:A,A4,Inventory!H:H) -> 0 | D4: =SUMIF(Inventory!A:A,A4,Inventory!I:I) -> 0 | E4: =SUMIF(Inventory!A:A,A4,Inventory!J:J) -> 150 | N4: Chloe | O4: =INDEX(Salary!E:E,4) -> 17810 | P4: =INDEX(Salary!F:F,4) -> 8905 | Q4: =INDEX(Salary!G:G,4) -> 16905
A5: Samsung | B5: =SUMIF(Inventory!A:A,A5,Inventory!G:G) -> 150 | C5: =SUMIF(Inventory!A:A,A5,Inventory!H:H) -> 23 | D5: =SUMIF(Inventory!A:A,A5,Inventory!I:I) -> 0 | E5: =SUMIF(Inventory!A:A,A5,Inventory!J:J) -> 127 | N5: Daniel | O5: =INDEX(Salary!E:E,5) -> 32890 | P5: =INDEX(Salary!F:F,5) -> 16445 | Q5: =INDEX(Salary!G:G,5) -> 24445
A6: Philips | B6: =SUMIF(Inventory!A:A,A6,Inventory!G:G) -> 150 | C6: =SUMIF(Inventory!A:A,A6,Inventory!H:H) -> 9 | D6: =SUMIF(Inventory!A:A,A6,Inventory!I:I) -> 0 | E6: =SUMIF(Inventory!A:A,A6,Inventory!J:J) -> 141 | N6: Ethan | O6: =INDEX(Salary!E:E,6) -> 53170 | P6: =INDEX(Salary!F:F,6) -> 26585 | Q6: =INDEX(Salary!G:G,6) -> 34585
A7: Sony | B7: =SUMIF(Inventory!A:A,A7,Inventory!G:G) -> 150 | C7: =SUMIF(Inventory!A:A,A7,Inventory!H:H) -> 16 | D7: =SUMIF(Inventory!A:A,A7,Inventory!I:I) -> 0 | E7: =SUMIF(Inventory!A:A,A7,Inventory!J:J) -> 134
A8: LG | B8: =SUMIF(Inventory!A:A,A8,Inventory!G:G) -> 150 | C8: =SUMIF(Inventory!A:A,A8,Inventory!H:H) -> 0 | D8: =SUMIF(Inventory!A:A,A8,Inventory!I:I) -> 0 | E8: =SUMIF(Inventory!A:A,A8,Inventory!J:J) -> 150
A9: Sharp | B9: =SUMIF(Inventory!A:A,A9,Inventory!G:G) -> 150 | C9: =SUMIF(Inventory!A:A,A9,Inventory!H:H) -> 7 | D9: =SUMIF(Inventory!A:A,A9,Inventory!I:I) -> 0 | E9: =SUMIF(Inventory!A:A,A9,Inventory!J:J) -> 143
A10: Xiaomi | B10: =SUMIF(Inventory!A:A,A10,Inventory!G:G) -> 150 | C10: =SUMIF(Inventory!A:A,A10,Inventory!H:H) -> 12 | D10: =SUMIF(Inventory!A:A,A10,Inventory!I:I) -> 0 | E10: =SUMIF(Inventory!A:A,A10,Inventory!J:J) -> 138
A11: Toshiba | B11: =SUMIF(Inventory!A:A,A11,Inventory!G:G) -> 150 | C11: =SUMIF(Inventory!A:A,A11,Inventory!H:H) -> 6 | D11: =SUMIF(Inventory!A:A,A11,Inventory!I:I) -> 0 | E11: =SUMIF(Inventory!A:A,A11,Inventory!J:J) -> 144
